pyordstat/__init__.py
pyordstat/base.py
pyordstat/continuous.py
pyordstat/core.py
pyordstat/discrete.py
pyordstat/finite.py
pyordstat/functions/__init__.py
pyordstat/functions/rv_continuous.py
pyordstat/functions/rv_discrete.py
pyordstat/py.typed
pyordstat-1.0.0.dist-info/LICENSE
pyordstat-1.0.0.dist-info/METADATA
pyordstat-1.0.0.dist-info/WHEEL
pyordstat-1.0.0.dist-info/RECORD
