Metadata-Version: 2.1
Name: pyordstat
Version: 1.0.0
Summary: Order statistics for Python
Home-page: https://github.com/stur86/pyordstat
Author: Simone Sturniolo
Author-email: simonesturniolo@gmail.com
Requires-Python: >=3.10,<3.13
Classifier: Programming Language :: Python :: 3
Classifier: Programming Language :: Python :: 3.10
Classifier: Programming Language :: Python :: 3.11
Requires-Dist: scipy (>=1.11.1,<2.0.0)
Project-URL: Repository, https://github.com/stur86/pyordstat
